commonthread/__init__.py
commonthread-0.33.dist-info/LICENSE.txt
commonthread-0.33.dist-info/METADATA
commonthread-0.33.dist-info/WHEEL
commonthread-0.33.dist-info/top_level.txt
commonthread-0.33.dist-info/RECORD
